__init__.py
jsonbox.py
jsonbox-1.2.1.dist-info/LICENSE
jsonbox-1.2.1.dist-info/METADATA
jsonbox-1.2.1.dist-info/WHEEL
jsonbox-1.2.1.dist-info/top_level.txt
jsonbox-1.2.1.dist-info/RECORD
