Metadata-Version: 2.1
Name: jsonbox
Version: 1.2.1
Summary: Python wrapper for jsonbox.io
Home-page: https://github.com/harlev/jsonbox-python
Author: Ron Harlev
Author-email: harlev@gmail.com
License: MIT
Platform: UNKNOWN
Classifier: Intended Audience :: Developers
Classifier: Operating System :: OS Independent
Classifier: Topic :: Software Development :: Libraries :: Python Modules
Classifier: Topic :: Internet
Classifier: License :: OSI Approved :: MIT License
Classifier: Programming Language :: Python :: 2.7
Classifier: Programming Language :: Python :: 3
Classifier: Programming Language :: Python :: 3.7
Requires-Python: >=2.7
Requires-Dist: requests
Requires-Dist: six
